windowspathadder/__init__.py
windowspathadder/__main__.py
windowspathadder/error.py
windowspathadder/windowspathadder.py
windows_path_adder-1.0.4.dist-info/LICENSE
windows_path_adder-1.0.4.dist-info/METADATA
windows_path_adder-1.0.4.dist-info/WHEEL
windows_path_adder-1.0.4.dist-info/top_level.txt
windows_path_adder-1.0.4.dist-info/RECORD
