Metadata-Version: 2.1
Name: windows-path-adder
Version: 1.0.4
Summary: add environment path in windows.
Home-page: https://github.com/oneofthezombies/windows-path-adder
Author: oneofthezombies
Author-email: hunhoekim@gmail.com
License: MIT
Platform: UNKNOWN
Classifier: Programming Language :: Python :: 3
Classifier: License :: OSI Approved :: MIT License
Classifier: Operating System :: OS Independent
